feed2toot/__init__.py
feed2toot/__main__.py
feed2toot/addtags.py
feed2toot/cli.py
feed2toot/cliparse.py
feed2toot/confparse.py
feed2toot/feedcache.py
feed2toot/filterentry.py
feed2toot/hashtags.py
feed2toot/lock.py
feed2toot/main.py
feed2toot/message.py
feed2toot/register_app.py
feed2toot/removeduplicates.py
feed2toot/rss.py
feed2toot/sortentries.py
feed2toot/tootpost.py
feed2toot/confparsers/__init__.py
feed2toot/confparsers/cache.py
feed2toot/confparsers/feedparser.py
feed2toot/confparsers/hashtaglist.py
feed2toot/confparsers/lock.py
feed2toot/confparsers/media.py
feed2toot/confparsers/plugins.py
feed2toot/confparsers/hashtags/__init__.py
feed2toot/confparsers/hashtags/nohashtags.py
feed2toot/confparsers/rss/__init__.py
feed2toot/confparsers/rss/addtags.py
feed2toot/confparsers/rss/ignoressl.py
feed2toot/confparsers/rss/pattern.py
feed2toot/confparsers/rss/toot.py
feed2toot/confparsers/rss/tootmaxlen.py
feed2toot/confparsers/rss/uri.py
feed2toot/confparsers/rss/urilist.py
feed2toot/plugins/__init__.py
feed2toot/plugins/influxdbplugin.py
feed2toot_oauth-1.0.2.dist-info/licenses/LICENSE
scripts/__init__.py
feed2toot_oauth-1.0.2.dist-info/METADATA
feed2toot_oauth-1.0.2.dist-info/WHEEL
feed2toot_oauth-1.0.2.dist-info/entry_points.txt
feed2toot_oauth-1.0.2.dist-info/top_level.txt
feed2toot_oauth-1.0.2.dist-info/RECORD
