Metadata-Version: 2.4
Name: feed2toot-oauth
Version: 1.0.2
Summary: Parse rss feeds and send new posts to Mastodon-likes
Home-page: https://github.com/theelous3/feed2toot-oauth
Download-URL: https://github.com/theelous3/feed2toot-oauth
Author: theelous3
Author-email: thee_grandmaster@hotmail.com
License: MIT
Classifier: Intended Audience :: End Users/Desktop
Classifier: Environment :: Console
Classifier: License :: OSI Approved :: GNU General Public License (GPL)
Classifier: Operating System :: POSIX :: Linux
Classifier: Programming Language :: Python :: 3.4
Classifier: Programming Language :: Python :: 3.5
Classifier: Programming Language :: Python :: 3.6
Classifier: Programming Language :: Python :: 3.7
License-File: LICENSE
Requires-Dist: beautifulsoup4
Requires-Dist: feedparser
Requires-Dist: Mastodon.py
Provides-Extra: influxdb
Requires-Dist: influxdb; extra == "influxdb"
Dynamic: author
Dynamic: author-email
Dynamic: classifier
Dynamic: description
Dynamic: download-url
Dynamic: home-page
Dynamic: license
Dynamic: license-file
Dynamic: provides-extra
Dynamic: requires-dist
Dynamic: summary
